qchem/Molecule.py
qchem/Parser.py
qchem/XYZFile.py
qchem/__init__.py
qchem/Calculation/BaseOrcaCalculation.py
qchem/Calculation/ClusterCalculation.py
qchem/Calculation/Frequency.py
qchem/Calculation/GOAT.py
qchem/Calculation/GeoOpt.py
qchem/Calculation/OrcaCalculation.py
qchem/Calculation/OrcaInputFile.py
qchem/Calculation/__init__.py
qchem/Data/Constants.py
qchem/Data/Enums.py
qchem/Data/__init__.py
qchem/Pipelines/Spectra.py
qchem/Pipelines/__init__.py
tests/FrequencyTest.py
tests/GeooptTest.py
tests/GoatTest.py
tests/__init__.py
tests/spectraTest.py
tests/test_parser.py
tests/test_random.py
qchem-0.54.0.dist-info/METADATA
qchem-0.54.0.dist-info/WHEEL
qchem-0.54.0.dist-info/top_level.txt
qchem-0.54.0.dist-info/RECORD
