Metadata-Version: 2.4
Name: qchem
Version: 0.54.0
Summary: A Quantum Chemistry Package for Python. Used and Created by the UW Formula Nano Team to design a Nano Car for the 2026/7 Nano Car Race
Home-page: https://github.com/UWFormulaN/qchem
Author: UWFormulaNano
Author-email: uwformulanano@gmail.com
Requires-Dist: numpy>=1.26.4
Requires-Dist: pandas>=2.2.2
Dynamic: author
Dynamic: author-email
Dynamic: description
Dynamic: description-content-type
Dynamic: home-page
Dynamic: requires-dist
Dynamic: summary
